amitava/__init__.py
aniket/__init__.py
ankita/__init__.py
controller/__init__.py
Amitava-0.1.1.dist-info/LICENSE
Amitava-0.1.1.dist-info/METADATA
Amitava-0.1.1.dist-info/WHEEL
Amitava-0.1.1.dist-info/top_level.txt
Amitava-0.1.1.dist-info/RECORD
